[
  {
  "month": 8,
   "gameId": 8231,
   "gameTitle": "Fire Emblem: Path of Radiance",
   "gameImageIcon": "/Images/100081.png",
   "gameImageTitle": "/Images/036332.png",
   "gameImageIngame": "/Images/036333.png",
   "gameImageBoxArt": "/Images/036334.png",
   "consoleID": 16,
   "consoleName": "GameCube",
   "achievementId": 394827,
   "achievementTitle": "Pirates!",
   "achievementDescription": "Clear 'Gallia'",
   "achievementBadgeName": "460422",
   "achievementDateStart": "2024-08-05T00:00:00.000000Z",
   "achievementDateEnd": "2024-09-02T00:00:00.000000Z"
  }
]
