[
  {
    "gameId": 9848,
    "gameTitle": "Action Man: Robot Atak",
    "gameImageIcon": "/Images/048949.png",
    "gameImageTitle": "/Images/082237.png",
    "gameImageIngame": "/Images/082239.png",
    "gameImageBoxArt": "/Images/015646.png",
    "consoleID": 5,
    "consoleName": "Game Boy Advance",
    "achievementId": 354286,
    "achievementTitle": "Adventure Man: Action Force Victory",
    "achievementDescription": "Complete the Dr X Battle on Adventure Mode (No Passwords)",
    "achievementBadgeName": "399242",
    "achievementDateStart": "2025-01-06T00:00:00.000000Z",
    "achievementDateEnd": "2025-01-13T00:00:00.000000Z",
    "swaps": [
      {
        "gameId": 111,
        "gameTitle": "Super Monaco GP",
        "gameImageIcon": "/Images/073396.png",
        "gameImageTitle": "/Images/001201.png",
        "gameImageIngame": "/Images/001203.png",
        "gameImageBoxArt": "/Images/001205.png",
        "consoleID": 1,
        "consoleName": "Genesis/Mega Drive",
        "achievementId": 21856,
        "achievementTitle": "U.S.A GP",
        "achievementDescription": "Finish first on the 6th round of the World Championship",
        "achievementBadgeName": "21745"
      },
      {
        "gameId": 13930,
        "gameTitle": "The Oregon Trail",
        "gameImageIcon": "/Images/084957.png",
        "gameImageTitle": "/Images/025879.png",
        "gameImageIngame": "/Images/025880.png",
        "gameImageBoxArt": "/Images/025881.png",
        "consoleID": 38,
        "consoleName": "Apple II",
        "achievementId": 368267,
        "achievementTitle": "Greenhorn",
        "achievementDescription": "Finish the trail as a Greenhorn or better",
        "achievementBadgeName": "414680"
      },
      {
        "gameId": 13830,
        "gameTitle": "Breakout | Breakaway IV",
        "gameImageIcon": "/Images/025725.png",
        "gameImageTitle": "/Images/025723.png",
        "gameImageIngame": "/Images/025724.png",
        "gameImageBoxArt": "/Images/025726.png",
        "consoleID": 25,
        "consoleName": "Atari 2600",
        "achievementId": 480330,
        "achievementTitle": "Normal Mode - Second Wall",
        "achievementDescription": "Reach 864pts in game 1 - 1 player",
        "achievementBadgeName": "544742"
      },
      {
        "gameId": 29769,
        "gameTitle": "Tower of Doom",
        "gameImageIcon": "/Images/096587.png",
        "gameImageTitle": "/Images/096402.png",
        "gameImageIngame": "/Images/096403.png",
        "gameImageBoxArt": "/Images/096404.png",
        "consoleID": 45,
        "consoleName": "Intellivision",
        "achievementId": 427356,
        "achievementTitle": "The Tower",
        "achievementDescription": "Escape the Tower after passing through at least 8 floors",
        "achievementBadgeName": "482576"
      }
    ]
  },
  {
    "gameId": 20599,
    "gameTitle": "Metal Slug 5",
    "gameImageIcon": "/Images/062439.png",
    "gameImageTitle": "/Images/062435.png",
    "gameImageIngame": "/Images/062436.png",
    "gameImageBoxArt": "/Images/062442.png",
    "consoleID": 21,
    "consoleName": "PlayStation 2",
    "achievementId": 358633,
    "achievementTitle": "Hell of an Ending",
    "achievementDescription": "Clear Final Mission in Arcade Mode",
    "achievementBadgeName": "404040",
    "achievementDateStart": "2025-01-13T00:00:00.000000Z",
    "achievementDateEnd": "2025-01-20T00:00:00.000000Z",
    "swaps": [
      {
        "gameId": 1095,
        "gameTitle": "Phalanx: The Enforce Fighter A-144",
        "gameImageIcon": "/Images/102906.png",
        "gameImageTitle": "/Images/004191.png",
        "gameImageIngame": "/Images/004192.png",
        "gameImageBoxArt": "/Images/048497.png",
        "consoleID": 3,
        "consoleName": "SNES/Super Famicom",
        "achievementId": 467025,
        "achievementTitle": "Rocky Experience",
        "achievementDescription": "Beat Mission 4: Deep Core on any difficulty.",
        "achievementBadgeName": "552601"
      },
      {
        "gameId": 1159,
        "gameTitle": "Saiyuki: Journey West",
        "gameImageIcon": "/Images/067979.png",
        "gameImageTitle": "/Images/034974.png",
        "gameImageIngame": "/Images/034972.png",
        "gameImageBoxArt": "/Images/034973.png",
        "consoleID": 12,
        "consoleName": "PlayStation",
        "achievementId": 119609,
        "achievementTitle": "The Lonely Warrior",
        "achievementDescription": "Complete story battle in Grace Spring",
        "achievementBadgeName": "130564"
      },
      {
        "gameId": 22757,
        "gameTitle": "Dragon Egg!",
        "gameImageIcon": "/Images/073325.png",
        "gameImageTitle": "/Images/073319.png",
        "gameImageIngame": "/Images/073320.png",
        "gameImageBoxArt": "/Images/073318.png",
        "consoleID": 8,
        "consoleName": "PC Engine/TurboGrafx-16",
        "achievementId": 361411,
        "achievementTitle": "Stage 6",
        "achievementDescription": "Clear Stage 6",
        "achievementBadgeName": "406729"
      },
      {
        "gameId": 28436,
        "gameTitle": "~Homebrew~ Phenix Corrupta",
        "gameImageIcon": "/Images/093393.png",
        "gameImageTitle": "/Images/093400.png",
        "gameImageIngame": "/Images/093401.png",
        "gameImageBoxArt": "/Images/000002.png",
        "consoleID": 29,
        "consoleName": "MSX",
        "achievementId": 413432,
        "achievementTitle": "Send Me Back",
        "achievementDescription": "Escape from hell.",
        "achievementBadgeName": "468035"
      }
    ]
  },
  {
    "gameId": 3351,
    "gameTitle": "Panel de Pon",
    "gameImageIcon": "/Images/065059.png",
    "gameImageTitle": "/Images/015296.png",
    "gameImageIngame": "/Images/015297.png",
    "gameImageBoxArt": "/Images/064929.png",
    "consoleID": 3,
    "consoleName": "SNES/Super Famicom",
    "achievementId": 270733,
    "achievementTitle": "Same Time, Same Panel",
    "achievementDescription": "Clear Vs. Mode (Any Difficulty)",
    "achievementBadgeName": "299501",
    "achievementDateStart": "2025-01-20T00:00:00.000000Z",
    "achievementDateEnd": "2025-01-27T00:00:00.000000Z",
    "swaps": [
      {
        "gameId": 23834,
        "gameTitle": "Double Dragon",
        "gameImageIcon": "/Images/080153.png",
        "gameImageTitle": "/Images/080149.png",
        "gameImageIngame": "/Images/080150.png",
        "gameImageBoxArt": "/Images/080148.png",
        "consoleID": 56,
        "consoleName": "Neo Geo CD",
        "achievementId": 367746,
        "achievementTitle": "The New Dark Master",
        "achievementDescription": "Beat the game as Abobo on any diffculty(Default Handicap, Two Rounds)",
        "achievementBadgeName": "414812"
      },
      {
        "gameId": 7193,
        "gameTitle": "Fushigi no Yume no Alice",
        "gameImageIcon": "/Images/079207.png",
        "gameImageTitle": "/Images/006940.png",
        "gameImageIngame": "/Images/006941.png",
        "gameImageBoxArt": "/Images/006944.png",
        "consoleID": 8,
        "consoleName": "PC Engine/TurboGrafx-16",
        "achievementId": 405287,
        "achievementTitle": "Requiem for a Dream",
        "achievementDescription": "Defeat the boss of Falls 3",
        "achievementBadgeName": "458559"
      },
      {
        "gameId": 1184,
        "gameTitle": "Star Trek: Deep Space Nine - Crossroads of Time",
        "gameImageIcon": "/Images/077472.png",
        "gameImageTitle": "/Images/008914.png",
        "gameImageIngame": "/Images/008915.png",
        "gameImageBoxArt": "/Images/008917.png",
        "consoleID": 3,
        "consoleName": "SNES/Super Famicom",
        "achievementId": 138612,
        "achievementTitle": "Contemplating Prophecy",
        "achievementDescription": "Find out what you can about the Redemptionists, then head to Bajor to rescue the Kai",
        "achievementBadgeName": "154274"
      },
      {
        "gameId": 17749,
        "gameTitle": "~Prototype~ Space Pinball",
        "gameImageIcon": "/Images/087330.png",
        "gameImageTitle": "/Images/044843.png",
        "gameImageIngame": "/Images/044844.png",
        "gameImageBoxArt": "/Images/044842.png",
        "consoleID": 28,
        "consoleName": "Virtual Boy",
        "achievementId": 419446,
        "achievementTitle": "To Boldly Go Where No One Has Gone Before!",
        "achievementDescription": "Transition from the 5th table with the UFO back to the 1st table with the diamond bumpers.",
        "achievementBadgeName": "477345"
      }
    ]
  },
  {
    "gameId": 2223,
    "gameTitle": "Kirby's Star Stacker",
    "gameImageIcon": "/Images/024368.png",
    "gameImageTitle": "/Images/040685.png",
    "gameImageIngame": "/Images/004643.png",
    "gameImageBoxArt": "/Images/064801.png",
    "consoleID": 4,
    "consoleName": "Game Boy",
    "achievementId": 23565,
    "achievementTitle": "Expert Stacker",
    "achievementDescription": "Complete all 16 levels of Round Clear mode on Very Hard difficulty",
    "achievementBadgeName": "125189",
    "achievementDateStart": "2025-01-27T00:00:00.000000Z",
    "achievementDateEnd": "2025-02-03T00:00:00.000000Z",
    "swaps": [
      {
        "gameId": 19020,
        "gameTitle": "Mortal Kombat: Deadly Alliance",
        "gameImageIcon": "/Images/064938.png",
        "gameImageTitle": "/Images/057355.png",
        "gameImageIngame": "/Images/057356.png",
        "gameImageBoxArt": "/Images/056153.png",
        "consoleID": 21,
        "consoleName": "PlayStation 2",
        "achievementId": 281226,
        "achievementTitle": "Mustard",
        "achievementDescription": "Finish Arcade Mode using only Cyrax.",
        "achievementBadgeName": "311041"
      },
      {
        "gameId": 3908,
        "gameTitle": "Star Ocean: First Departure",
        "gameImageIcon": "/Images/103361.png",
        "gameImageTitle": "/Images/065949.png",
        "gameImageIngame": "/Images/101962.png",
        "gameImageBoxArt": "/Images/054827.png",
        "consoleID": 41,
        "consoleName": "PlayStation Portable",
        "achievementId": 472229,
        "achievementTitle": "Permitted to Enter",
        "achievementDescription": "Successfully enter Portmith",
        "achievementBadgeName": "535211"
      },
      {
        "gameId": 4060,
        "gameTitle": "Black Belt Challenge",
        "gameImageIcon": "/Images/062340.png",
        "gameImageTitle": "/Images/041109.png",
        "gameImageIngame": "/Images/041108.png",
        "gameImageBoxArt": "/Images/041107.png",
        "consoleID": 5,
        "consoleName": "Game Boy Advance",
        "achievementId": 137570,
        "achievementTitle": "Steelfeather",
        "achievementDescription": "Finish Arcade Mode as Stahlfeder [Normal or higher | Default settings]",
        "achievementBadgeName": "152764"
      },
      {
        "gameId": 11979,
        "gameTitle": "U.N. Squadron",
        "gameImageIcon": "/Images/061639.png",
        "gameImageTitle": "/Images/061344.png",
        "gameImageIngame": "/Images/061342.png",
        "gameImageBoxArt": "/Images/061309.png",
        "consoleID": 27,
        "consoleName": "Arcade",
        "achievementId": 247831,
        "achievementTitle": "Mission 10: Project 4's Final Weapon",
        "achievementDescription": "Destroyed the Project 4 Flying Fortress in Mission 10 ('Normal' Difficulty or higher)",
        "achievementBadgeName": "274403"
      }
    ]
  },
  {
    "gameId": 19738,
    "gameTitle": "~Hack~ Quest of Hat",
    "gameImageIcon": "/Images/058265.png",
    "gameImageTitle": "/Images/058229.png",
    "gameImageIngame": "/Images/058230.png",
    "gameImageBoxArt": "/Images/058969.png",
    "consoleID": 3,
    "consoleName": "SNES/Super Famicom",
    "achievementId": 224763,
    "achievementTitle": "Poked Out",
    "achievementDescription": "Defeat Pokey and win the game.",
    "achievementBadgeName": "248298",
    "achievementDateStart": "2025-02-03T00:00:00.000000Z",
    "achievementDateEnd": "2025-02-10T00:00:00.000000Z",
    "swaps": [
      {
        "gameId": 17959,
        "gameTitle": "Guilty Gear Petit",
        "gameImageIcon": "/Images/048443.png",
        "gameImageTitle": "/Images/048441.png",
        "gameImageIngame": "/Images/048440.png",
        "gameImageBoxArt": "/Images/048442.png",
        "consoleID": 53,
        "consoleName": "WonderSwan",
        "achievementId": 175014,
        "achievementTitle": "Upgraded Colours",
        "achievementDescription": "Clear Story Mode as GG Millia [>=Normal | Standard Settings]",
        "achievementBadgeName": "245166"
      },
      {
        "gameId": 7766,
        "gameTitle": "Battle B-Daman",
        "gameImageIcon": "/Images/050590.png",
        "gameImageTitle": "/Images/050490.png",
        "gameImageIngame": "/Images/050491.png",
        "gameImageBoxArt": "/Images/050175.png",
        "consoleID": 5,
        "consoleName": "Game Boy Advance",
        "achievementId": 190168,
        "achievementTitle": "Tag Team",
        "achievementDescription": "Defeat Wen & Li for the first time at Ice Rock",
        "achievementBadgeName": "211090"
      },
      {
        "gameId": 10880,
        "gameTitle": "E-SWAT",
        "gameImageIcon": "/Images/015948.png",
        "gameImageTitle": "/Images/015585.png",
        "gameImageIngame": "/Images/015586.png",
        "gameImageBoxArt": "/Images/015587.png",
        "consoleID": 11,
        "consoleName": "Master System",
        "achievementId": 56828,
        "achievementTitle": "Round 5 - ??? Unknown",
        "achievementDescription": "Beat the round 5",
        "achievementBadgeName": "59344"
      },
      {
        "gameId": 2157,
        "gameTitle": "Warsong | Langrisser: The Descendants of Light",
        "gameImageIcon": "/Images/036363.png",
        "gameImageTitle": "/Images/014645.png",
        "gameImageIngame": "/Images/014650.png",
        "gameImageBoxArt": "/Images/036057.png",
        "consoleID": 1,
        "consoleName": "Genesis/Mega Drive",
        "achievementId": 121558,
        "achievementTitle": "Evilution",
        "achievementDescription": "Survive the slimy monsters of the forest in Scenario 4",
        "achievementBadgeName": "132709"
      }
    ]
  },
  {
    "gameId": 7777,
    "gameTitle": "Killer7",
    "gameImageIcon": "/Images/093417.png",
    "gameImageTitle": "/Images/093415.png",
    "gameImageIngame": "/Images/093416.png",
    "gameImageBoxArt": "/Images/093418.png",
    "consoleID": 16,
    "consoleName": "GameCube",
    "achievementId": 407754,
    "achievementTitle": "Seventh Heaven",
    "achievementDescription": "Complete Target 00 [Angel] in Killer7 mode and on any difficulty",
    "achievementBadgeName": "467631",
    "achievementDateStart": "2025-02-10T00:00:00.000000Z",
    "achievementDateEnd": "2025-02-17T00:00:00.000000Z",
    "swaps": [
      {
        "gameId": 12780,
        "gameTitle": "The Ren & Stimpy Show: Space Cadet Adventures",
        "gameImageIcon": "/Images/096038.png",
        "gameImageTitle": "/Images/016873.png",
        "gameImageIngame": "/Images/016874.png",
        "gameImageBoxArt": "/Images/016872.png",
        "consoleID": 4,
        "consoleName": "Game Boy",
        "achievementId": 422216,
        "achievementTitle": "Asteroid City Trailer Park Complete",
        "achievementDescription": "Finish the game by completing stage 4",
        "achievementBadgeName": "477636"
      },
      {
        "gameId": 22610,
        "gameTitle": "Saint Seiya: The Sanctuary",
        "gameImageIcon": "/Images/074668.png",
        "gameImageTitle": "/Images/075708.png",
        "gameImageIngame": "/Images/075709.png",
        "gameImageBoxArt": "/Images/074669.png",
        "consoleID": 21,
        "consoleName": "PlayStation 2",
        "achievementId": 330337,
        "achievementTitle": "Warriors, I entrust Athena to you",
        "achievementDescription": "Finish the story Will of Aiolos. (Normal+)",
        "achievementBadgeName": "372625"
      },
      {
        "gameId": 16532,
        "gameTitle": "~Homebrew~ Aperture Science DS | Portal DS",
        "gameImageIcon": "/Images/061425.png",
        "gameImageTitle": "/Images/036325.png",
        "gameImageIngame": "/Images/036327.png",
        "gameImageBoxArt": "/Images/036324.png",
        "consoleID": 18,
        "consoleName": "Nintendo DS",
        "achievementId": 244624,
        "achievementTitle": "Final Test",
        "achievementDescription": "Solve Test Chamber 14.",
        "achievementBadgeName": "271441"
      },
      {
        "gameId": 16528,
        "gameTitle": "Super Street Fighter II Turbo",
        "gameImageIcon": "/Images/070133.png",
        "gameImageTitle": "/Images/036283.png",
        "gameImageIngame": "/Images/036402.png",
        "gameImageBoxArt": "/Images/036284.png",
        "consoleID": 43,
        "consoleName": "3DO Interactive Multiplayer",
        "achievementId": 121958,
        "achievementTitle": "The King of Chaos",
        "achievementDescription": "Beat Super Battle as M.Bison on default difficulty or higher",
        "achievementBadgeName": "133637"
      }
    ]
  },
  {
    "gameId": 572,
    "gameTitle": "Magical Quest 3 starring Mickey & Donald",
    "gameImageIcon": "/Images/051485.png",
    "gameImageTitle": "/Images/008357.png",
    "gameImageIngame": "/Images/008356.png",
    "gameImageBoxArt": "/Images/014449.png",
    "consoleID": 5,
    "consoleName": "Game Boy Advance",
    "achievementId": 37092,
    "achievementTitle": "Pete Castle-Donald",
    "achievementDescription": "Complete the Game as Donald Duck",
    "achievementBadgeName": "37839",
    "achievementDateStart": "2025-02-17T00:00:00.000000Z",
    "achievementDateEnd": "2025-02-24T00:00:00.000000Z",
    "swaps": [
      {
        "gameId": 4941,
        "gameTitle": "One",
        "gameImageIcon": "/Images/082577.png",
        "gameImageTitle": "/Images/082580.png",
        "gameImageIngame": "/Images/082579.png",
        "gameImageBoxArt": "/Images/082578.png",
        "consoleID": 12,
        "consoleName": "PlayStation",
        "achievementId": 447900,
        "achievementTitle": "Mountain Fortress",
        "achievementDescription": "Clear Stage Three on Normal difficulty or above.",
        "achievementBadgeName": "533398"
      },
      {
        "gameId": 258,
        "gameTitle": "Dick Tracy",
        "gameImageIcon": "/Images/072796.png",
        "gameImageTitle": "/Images/039429.png",
        "gameImageIngame": "/Images/039430.png",
        "gameImageBoxArt": "/Images/069645.png",
        "consoleID": 1,
        "consoleName": "Genesis/Mega Drive",
        "achievementId": 297575,
        "achievementTitle": "Where's Big Boy...",
        "achievementDescription": "Complete Stage 4 Scene C on Normal difficulty or higher",
        "achievementBadgeName": "19363"
      },
      {
        "gameId": 3398,
        "gameTitle": "Shenmue",
        "gameImageIcon": "/Images/053854.png",
        "gameImageTitle": "/Images/087470.png",
        "gameImageIngame": "/Images/087471.png",
        "gameImageBoxArt": "/Images/053080.png",
        "consoleID": 40,
        "consoleName": "Dreamcast",
        "achievementId": 376808,
        "achievementTitle": "Ah Shit, Here We Go Again",
        "achievementDescription": "Get the initial tip on asking around for sailors [Story]",
        "achievementBadgeName": "423351"
      },
      {
        "gameId": 2671,
        "gameTitle": "Rogue Galaxy",
        "gameImageIcon": "/Images/056026.png",
        "gameImageTitle": "/Images/056025.png",
        "gameImageIngame": "/Images/056023.png",
        "gameImageBoxArt": "/Images/056024.png",
        "consoleID": 21,
        "consoleName": "PlayStation 2",
        "achievementId": 281474,
        "achievementTitle": "Whoop There It Is",
        "achievementDescription": "Defeat the Mud Whooper on Juriaka",
        "achievementBadgeName": "311500"
      }
    ]
  },
  {
    "gameId": 10093,
    "gameTitle": "Hexen",
    "gameImageIcon": "/Images/055046.png",
    "gameImageTitle": "/Images/010999.png",
    "gameImageIngame": "/Images/011000.png",
    "gameImageBoxArt": "/Images/014510.png",
    "consoleID": 2,
    "consoleName": "Nintendo 64",
    "achievementId": 48615,
    "achievementTitle": "Shadow Wood",
    "achievementDescription": "Enter the second hub Shadow Wood",
    "achievementBadgeName": "362977",
    "achievementDateStart": "2025-02-24T00:00:00.000000Z",
    "achievementDateEnd": "2025-03-03T00:00:00.000000Z",
    "swaps": [
      {
        "gameId": 5345,
        "gameTitle": "Shark Tale",
        "gameImageIcon": "/Images/066642.png",
        "gameImageTitle": "/Images/066641.png",
        "gameImageIngame": "/Images/066640.png",
        "gameImageBoxArt": "/Images/066512.png",
        "consoleID": 5,
        "consoleName": "Game Boy Advance",
        "achievementId": 282286,
        "achievementTitle": "Wealth and Fame",
        "achievementDescription": "Complete chapter 3.",
        "achievementBadgeName": "312471"
      },
      {
        "gameId": 12358,
        "gameTitle": "Rally-X",
        "gameImageIcon": "/Images/067917.png",
        "gameImageTitle": "/Images/067879.png",
        "gameImageIngame": "/Images/067880.png",
        "gameImageBoxArt": "/Images/067881.png",
        "consoleID": 27,
        "consoleName": "Arcade",
        "achievementId": 287981,
        "achievementTitle": "Turn Left in 2 Miles",
        "achievementDescription": "Complete Round 6 and reach the second Charging Station",
        "achievementBadgeName": "319158"
      },
      {
        "gameId": 485,
        "gameTitle": "Arcus Odyssey",
        "gameImageIcon": "/Images/050154.png",
        "gameImageTitle": "/Images/049875.png",
        "gameImageIngame": "/Images/049876.png",
        "gameImageBoxArt": "/Images/011944.png",
        "consoleID": 1,
        "consoleName": "Genesis/Mega Drive",
        "achievementId": 181911,
        "achievementTitle": "Revival",
        "achievementDescription": "Clear Act 4 [No Passwords]",
        "achievementBadgeName": "202378"
      },
      {
        "gameId": 5707,
        "gameTitle": "Hot Wheels: Burnin' Rubber",
        "gameImageIcon": "/Images/096234.png",
        "gameImageTitle": "/Images/070358.png",
        "gameImageIngame": "/Images/070359.png",
        "gameImageBoxArt": "/Images/070357.png",
        "consoleID": 5,
        "consoleName": "Game Boy Advance",
        "achievementId": 424327,
        "achievementTitle": "Lakester",
        "achievementDescription": "Complete the silver cup to unlock the Lakester car",
        "achievementBadgeName": "479598"
      }
    ]
  },
  {
    "gameId": 22113,
    "gameTitle": "Suggoi! Arcana Heart 2",
    "gameImageIcon": "/Images/081841.png",
    "gameImageTitle": "/Images/081330.png",
    "gameImageIngame": "/Images/081464.png",
    "gameImageBoxArt": "/Images/081347.png",
    "consoleID": 21,
    "consoleName": "PlayStation 2",
    "achievementId": 350736,
    "achievementTitle": "Arcana Arcade Adventure!!",
    "achievementDescription": "Finish Arcade Mode (default settings).",
    "achievementBadgeName": "396311",
    "achievementDateStart": "2025-03-03T00:00:00.000000Z",
    "achievementDateEnd": "2025-03-10T00:00:00.000000Z",
    "swaps": [
      {
        "gameId": 17560,
        "gameTitle": "Gear Fighter Dendoh",
        "gameImageIcon": "/Images/048525.png",
        "gameImageTitle": "/Images/043076.png",
        "gameImageIngame": "/Images/043077.png",
        "gameImageBoxArt": "/Images/048883.png",
        "consoleID": 12,
        "consoleName": "PlayStation",
        "achievementId": 176874,
        "achievementTitle": "Takeoff! To Space",
        "achievementDescription": "Complete lvl 7",
        "achievementBadgeName": "197187"
      },
      {
        "gameId": 10424,
        "gameTitle": "Power Rangers: Time Force",
        "gameImageIcon": "/Images/014217.png",
        "gameImageTitle": "/Images/014215.png",
        "gameImageIngame": "/Images/014216.png",
        "gameImageBoxArt": "/Images/014214.png",
        "consoleID": 6,
        "consoleName": "Game Boy Color",
        "achievementId": 201656,
        "achievementTitle": "Fabled City (Present Day)",
        "achievementDescription": "Complete Fabled City (Present Day) Level (on Normal or less)",
        "achievementBadgeName": "223924"
      },
      {
        "gameId": 858,
        "gameTitle": "Claymates",
        "gameImageIcon": "/Images/103874.png",
        "gameImageTitle": "/Images/022839.png",
        "gameImageIngame": "/Images/022840.png",
        "gameImageBoxArt": "/Images/022841.png",
        "consoleID": 3,
        "consoleName": "SNES/Super Famicom",
        "achievementId": 465911,
        "achievementTitle": "Full Grid on Medium",
        "achievementDescription": "Complete the grid bonus game in the Pacific or later.",
        "achievementBadgeName": "534361"
      },
      {
        "gameId": 2052,
        "gameTitle": "Ultima: Warriors of Destiny",
        "gameImageIcon": "/Images/029825.png",
        "gameImageTitle": "/Images/013228.png",
        "gameImageIngame": "/Images/013229.png",
        "gameImageBoxArt": "/Images/012631.png",
        "consoleID": 7,
        "consoleName": "NES/Famicom",
        "achievementId": 94824,
        "achievementTitle": "Member of the Resistance",
        "achievementDescription": "Learn the Resistance Password",
        "achievementBadgeName": "104327"
      }
    ]
  },
  {
    "gameId": 9722,
    "gameTitle": "Sabrina: The Animated Series - Zapped!",
    "gameImageIcon": "/Images/102589.png",
    "gameImageTitle": "/Images/102632.png",
    "gameImageIngame": "/Images/102633.png",
    "gameImageBoxArt": "/Images/090611.png",
    "consoleID": 6,
    "consoleName": "Game Boy Color",
    "achievementId": 465599,
    "achievementTitle": "All the Monkeys in the House Go Yeah",
    "achievementDescription": "Transform gorilla Slugloafe back into a human",
    "achievementBadgeName": "526918",
    "achievementDateStart": "2025-03-10T00:00:00.000000Z",
    "achievementDateEnd": "2025-03-17T00:00:00.000000Z",
    "swaps": [
      {
        "gameId": 16,
        "gameTitle": "Super Hang-On",
        "gameImageIcon": "/Images/000860.png",
        "gameImageTitle": "/Images/000712.png",
        "gameImageIngame": "/Images/000713.png",
        "gameImageBoxArt": "/Images/051933.png",
        "consoleID": 1,
        "consoleName": "Genesis/Mega Drive",
        "achievementId": 4358,
        "achievementTitle": "A Well-Deserved Smooch",
        "achievementDescription": "Arcade Mode - Complete the Junior Course without using passwords",
        "achievementBadgeName": "04994"
      },
      {
        "gameId": 5706,
        "gameTitle": "Mech Platoon",
        "gameImageIcon": "/Images/063425.png",
        "gameImageTitle": "/Images/050178.png",
        "gameImageIngame": "/Images/050177.png",
        "gameImageBoxArt": "/Images/063424.png",
        "consoleID": 5,
        "consoleName": "Game Boy Advance",
        "achievementId": 261180,
        "achievementTitle": "Flow",
        "achievementDescription": "Clear the mission 'Ebb Tide' with the Leon Army",
        "achievementBadgeName": "289348"
      },
      {
        "gameId": 19201,
        "gameTitle": "Mortal Kombat: Shaolin Monks",
        "gameImageIcon": "/Images/079497.png",
        "gameImageTitle": "/Images/061950.png",
        "gameImageIngame": "/Images/061951.png",
        "gameImageBoxArt": "/Images/056629.png",
        "consoleID": 21,
        "consoleName": "PlayStation 2",
        "achievementId": 270342,
        "achievementTitle": "The Portal (Kung Lao)",
        "achievementDescription": "Enter The Portal for the first time as Kung Lao.",
        "achievementBadgeName": "299106"
      },
      {
        "gameId": 19201,
        "gameTitle": "Mortal Kombat: Shaolin Monks",
        "gameImageIcon": "/Images/079497.png",
        "gameImageTitle": "/Images/061950.png",
        "gameImageIngame": "/Images/061951.png",
        "gameImageBoxArt": "/Images/056629.png",
        "consoleID": 21,
        "consoleName": "PlayStation 2",
        "achievementId": 270343,
        "achievementTitle": "The Portal (Liu Kang)",
        "achievementDescription": "Enter The Portal for the first time as Liu Kang.",
        "achievementBadgeName": "299107"
      },
      {
        "gameId": 2655,
        "gameTitle": "Shin Megami Tensei: Nocturne",
        "gameImageIcon": "/Images/084331.png",
        "gameImageTitle": "/Images/084924.png",
        "gameImageIngame": "/Images/084923.png",
        "gameImageBoxArt": "/Images/072378.png",
        "consoleID": 21,
        "consoleName": "PlayStation 2",
        "achievementId": 411373,
        "achievementTitle": "Me EaT YoU!",
        "achievementDescription": "[NG] Defeat the Specter in the Amala Network",
        "achievementBadgeName": "465811"
      }
    ]
  },
  {
    "gameId": 20645,
    "gameTitle": "Polaroid Pete | Gekibo: Gekisha Boy 2",
    "gameImageIcon": "/Images/064052.png",
    "gameImageTitle": "/Images/064053.png",
    "gameImageIngame": "/Images/064054.png",
    "gameImageBoxArt": "/Images/064055.png",
    "consoleID": 21,
    "consoleName": "PlayStation 2",
    "achievementId": 280251,
    "achievementTitle": "Shashin no Kuni",
    "achievementDescription": "Successfully capture the objective in Historic Town Tsukiji. [>= Normal]",
    "achievementBadgeName": "310009",
    "achievementDateStart": "2025-03-17T00:00:00.000000Z",
    "achievementDateEnd": "2025-03-24T00:00:00.000000Z",
    "swaps": [
      {
        "gameId": 1980,
        "gameTitle": "Star Trek: 25th Anniversary",
        "gameImageIcon": "/Images/077471.png",
        "gameImageTitle": "/Images/009142.png",
        "gameImageIngame": "/Images/009143.png",
        "gameImageBoxArt": "/Images/013049.png",
        "consoleID": 7,
        "consoleName": "NES/Famicom",
        "achievementId": 75891,
        "achievementTitle": "I Am Lying",
        "achievementDescription": "Find the red module",
        "achievementBadgeName": "215140"
      },
      {
        "gameId": 2705,
        "gameTitle": "Brandish 2: The Planet Buster",
        "gameImageIcon": "/Images/086293.png",
        "gameImageTitle": "/Images/059352.png",
        "gameImageIngame": "/Images/059353.png",
        "gameImageBoxArt": "/Images/059351.png",
        "consoleID": 3,
        "consoleName": "SNES/Super Famicom",
        "achievementId": 227332,
        "achievementTitle": "Rakshasa",
        "achievementDescription": "Defeat the Rakshasa in the prison.",
        "achievementBadgeName": "252303"
      },
      {
        "gameId": 17707,
        "gameTitle": "Arcade Gears Vol. 1: Pu-Li-Ru-La",
        "gameImageIcon": "/Images/088536.png",
        "gameImageTitle": "/Images/088534.png",
        "gameImageIngame": "/Images/088535.png",
        "gameImageBoxArt": "/Images/088533.png",
        "consoleID": 39,
        "consoleName": "Saturn",
        "achievementId": 392895,
        "achievementTitle": "End of the World",
        "achievementDescription": "Defeat Jack O'Colson for real on normal or hard! (Other settings default or lower, ura mode off)",
        "achievementBadgeName": "443905"
      },
      {
        "gameId": 1179,
        "gameTitle": "Spider-Man & Venom: Maximum Carnage",
        "gameImageIcon": "/Images/105532.png",
        "gameImageTitle": "/Images/003623.png",
        "gameImageIngame": "/Images/003621.png",
        "gameImageBoxArt": "/Images/039425.png",
        "consoleID": 3,
        "consoleName": "SNES/Super Famicom",
        "achievementId": 18279,
        "achievementTitle": "The Fearsome Five",
        "achievementDescription": "Clear Level 13 - Prospect Park 2",
        "achievementBadgeName": "17769"
      }
    ]
  },
  {
    "gameId": 14814,
    "gameTitle": "Mario vs. Donkey Kong 2: March of the Minis",
    "gameImageIcon": "/Images/070183.png",
    "gameImageTitle": "/Images/076619.png",
    "gameImageIngame": "/Images/076620.png",
    "gameImageBoxArt": "/Images/028966.png",
    "consoleID": 18,
    "consoleName": "Nintendo DS",
    "achievementId": 334651,
    "achievementTitle": "Magnetic Mastery",
    "achievementDescription": "Defeat Donkey Kong in Magnet Mania",
    "achievementBadgeName": "377737",
    "achievementDateStart": "2025-03-24T00:00:00.000000Z",
    "achievementDateEnd": "2025-03-31T00:00:00.000000Z",
    "swaps": [
      {
        "gameId": 14544,
        "gameTitle": "Shining Wisdom",
        "gameImageIcon": "/Images/079407.png",
        "gameImageTitle": "/Images/031644.png",
        "gameImageIngame": "/Images/031645.png",
        "gameImageBoxArt": "/Images/031643.png",
        "consoleID": 39,
        "consoleName": "Saturn",
        "achievementId": 100523,
        "achievementTitle": "Sliding man",
        "achievementDescription": "Find the Slide Shoes",
        "achievementBadgeName": "109623"
      },
      {
        "gameId": 1517,
        "gameTitle": "A Nightmare on Elm Street",
        "gameImageIcon": "/Images/061836.png",
        "gameImageTitle": "/Images/006080.png",
        "gameImageIngame": "/Images/006081.png",
        "gameImageBoxArt": "/Images/012665.png",
        "consoleID": 7,
        "consoleName": "NES/Famicom",
        "achievementId": 29601,
        "achievementTitle": "The Abandoned House",
        "achievementDescription": "Defeat the enemy, collect all bones and the key in the Abandoned House",
        "achievementBadgeName": "30236"
      },
      {
        "gameId": 16210,
        "gameTitle": "Bare Knuckle III",
        "gameImageIcon": "/Images/049209.png",
        "gameImageTitle": "/Images/032981.png",
        "gameImageIngame": "/Images/032982.png",
        "gameImageBoxArt": "/Images/032984.png",
        "consoleID": 1,
        "consoleName": "Genesis/Mega Drive",
        "achievementId": 107959,
        "achievementTitle": "Crazy Train",
        "achievementDescription": "Defeat Jet and his rocket squad in Round 6",
        "achievementBadgeName": "117439"
      },
      {
        "gameId": 19217,
        "gameTitle": "Gungage",
        "gameImageIcon": "/Images/072311.png",
        "gameImageTitle": "/Images/056352.png",
        "gameImageIngame": "/Images/056350.png",
        "gameImageBoxArt": "/Images/056351.png",
        "consoleID": 12,
        "consoleName": "PlayStation",
        "achievementId": 312572,
        "achievementTitle": "Fully Maxed",
        "achievementDescription": "Upgrade max health 3 times in the same campaign",
        "achievementBadgeName": "347592"
      }
    ]
  },
  {
    "gameId": 2672,
    "gameTitle": "We Love Katamari",
    "gameImageIcon": "/Images/057479.png",
    "gameImageTitle": "/Images/057453.png",
    "gameImageIngame": "/Images/035542.png",
    "gameImageBoxArt": "/Images/058275.png",
    "consoleID": 21,
    "consoleName": "PlayStation 2",
    "achievementId": 225698,
    "achievementTitle": "You're A Planet In My Heart",
    "achievementDescription": "Create Pluto.",
    "achievementBadgeName": "249930",
    "achievementDateStart": "2025-03-31T00:00:00.000000Z",
    "achievementDateEnd": "2025-04-07T00:00:00.000000Z",
    "swaps": [
      {
        "gameId": 4680,
        "gameTitle": "Pizza Pop!",
        "gameImageIcon": "/Images/052580.png",
        "gameImageTitle": "/Images/002218.png",
        "gameImageIngame": "/Images/002217.png",
        "gameImageBoxArt": "/Images/013993.png",
        "consoleID": 7,
        "consoleName": "NES/Famicom",
        "achievementId": 9647,
        "achievementTitle": "Stage 7",
        "achievementDescription": "Beat Stage 7",
        "achievementBadgeName": "09309"
      },
      {
        "gameId": 2370,
        "gameTitle": "~Prototype~ Resident Evil",
        "gameImageIcon": "/Images/040116.png",
        "gameImageTitle": "/Images/016487.png",
        "gameImageIngame": "/Images/016486.png",
        "gameImageBoxArt": "/Images/045393.png",
        "consoleID": 6,
        "consoleName": "Game Boy Color",
        "achievementId": 67783,
        "achievementTitle": "Jill's Dead End",
        "achievementDescription": "[Jill Valentine] Activate the Generator and try to use the Elevator.",
        "achievementBadgeName": "71808"
      },
      {
        "gameId": 2370,
        "gameTitle": "~Prototype~ Resident Evil",
        "gameImageIcon": "/Images/040116.png",
        "gameImageTitle": "/Images/016487.png",
        "gameImageIngame": "/Images/016486.png",
        "gameImageBoxArt": "/Images/045393.png",
        "consoleID": 6,
        "consoleName": "Game Boy Color",
        "achievementId": 67773,
        "achievementTitle": "Chris' Dead End",
        "achievementDescription": "[Chris Redfield] Activate the Generator and try to use the Elevator.",
        "achievementBadgeName": "71803"
      },
      {
        "gameId": 6623,
        "gameTitle": "Scooby-Doo 2: Monsters Unleashed",
        "gameImageIcon": "/Images/108664.png",
        "gameImageTitle": "/Images/047826.png",
        "gameImageIngame": "/Images/047827.png",
        "gameImageBoxArt": "/Images/047829.png",
        "consoleID": 5,
        "consoleName": "Game Boy Advance",
        "achievementId": 178847,
        "achievementTitle": "Power Outage",
        "achievementDescription": "Short out the 10,000 Volt Ghost.",
        "achievementBadgeName": "199244"
      },
      {
        "gameId": 16374,
        "gameTitle": "Gekibo: Gekisha Boy",
        "gameImageIcon": "/Images/074867.png",
        "gameImageTitle": "/Images/038191.png",
        "gameImageIngame": "/Images/038192.png",
        "gameImageBoxArt": "/Images/074869.png",
        "consoleID": 8,
        "consoleName": "PC Engine/TurboGrafx-16",
        "achievementId": 326910,
        "achievementTitle": "Graduation Exam",
        "achievementDescription": "Complete TAKE 09 with 150,000 points or more.",
        "achievementBadgeName": "366065"
      }
    ]
  },
  {
    "gameId": 5119,
    "gameTitle": "Tokyo Xtreme Racer Advance",
    "gameImageIcon": "/Images/095550.png",
    "gameImageTitle": "/Images/053477.png",
    "gameImageIngame": "/Images/053482.png",
    "gameImageBoxArt": "/Images/053479.png",
    "consoleID": 5,
    "consoleName": "Game Boy Advance",
    "achievementId": 200860,
    "achievementTitle": "Knights",
    "achievementDescription": "Defeat all Knights rivals.",
    "achievementBadgeName": "223125",
    "achievementDateStart": "2025-04-07T00:00:00.000000Z",
    "achievementDateEnd": "2025-04-14T00:00:00.000000Z",
    "swaps": [
      {
        "gameId": 1477,
        "gameTitle": "Jackal",
        "gameImageIcon": "/Images/063214.png",
        "gameImageTitle": "/Images/035312.png",
        "gameImageIngame": "/Images/035313.png",
        "gameImageBoxArt": "/Images/012319.png",
        "consoleID": 7,
        "consoleName": "NES/Famicom",
        "achievementId": 15102,
        "achievementTitle": "Jackal Unleashed!",
        "achievementDescription": "Destroy the Final Boss!",
        "achievementBadgeName": "14771"
      },
      {
        "gameId": 16755,
        "gameTitle": "Orcs and Elves",
        "gameImageIcon": "/Images/056285.png",
        "gameImageTitle": "/Images/056284.png",
        "gameImageIngame": "/Images/056485.png",
        "gameImageBoxArt": "/Images/056286.png",
        "consoleID": 18,
        "consoleName": "Nintendo DS",
        "achievementId": 215727,
        "achievementTitle": "Prison Delver",
        "achievementDescription": "Make it through level 2. (Any difficulty)",
        "achievementBadgeName": "238781"
      },
      {
        "gameId": 6394,
        "gameTitle": "Hammerin' Harry",
        "gameImageIcon": "/Images/013280.png",
        "gameImageTitle": "/Images/013281.png",
        "gameImageIngame": "/Images/013282.png",
        "gameImageBoxArt": "/Images/013279.png",
        "consoleID": 7,
        "consoleName": "NES/Famicom",
        "achievementId": 70786,
        "achievementTitle": "Freed from Greed",
        "achievementDescription": "Beat Stage 5",
        "achievementBadgeName": "75804"
      },
      {
        "gameId": 4187,
        "gameTitle": "Donald Duck: Goin' Quackers",
        "gameImageIcon": "/Images/072505.png",
        "gameImageTitle": "/Images/040643.png",
        "gameImageIngame": "/Images/072508.png",
        "gameImageBoxArt": "/Images/026224.png",
        "consoleID": 6,
        "consoleName": "Game Boy Color",
        "achievementId": 134537,
        "achievementTitle": "Duckburg",
        "achievementDescription": "Cleared all levels in World 2. [Password allowed, ONLY for 2-1]",
        "achievementBadgeName": "149022"
      }
    ]
  },
  {
    "gameId": 4969,
    "gameTitle": "Super Mario World: Super Mario Advance 2",
    "gameImageIcon": "/Images/039083.png",
    "gameImageTitle": "/Images/007070.png",
    "gameImageIngame": "/Images/007067.png",
    "gameImageBoxArt": "/Images/007066.png",
    "consoleID": 5,
    "consoleName": "Game Boy Advance",
    "achievementId": 37552,
    "achievementTitle": "Cookie Mountain Crumbled",
    "achievementDescription": "Defeat Ludwig Von Koopa in Cookie Mountain",
    "achievementBadgeName": "412123",
    "achievementDateStart": "2025-04-14T00:00:00.000000Z",
    "achievementDateEnd": "2025-04-21T00:00:00.000000Z",
    "swaps": [
      {
        "gameId": 25460,
        "gameTitle": "Odama",
        "gameImageIcon": "/Images/082274.png",
        "gameImageTitle": "/Images/082272.png",
        "gameImageIngame": "/Images/082273.png",
        "gameImageBoxArt": "/Images/081366.png",
        "consoleID": 16,
        "consoleName": "GameCube",
        "achievementId": 443991,
        "achievementTitle": "Open the Floodgates!",
        "achievementDescription": "Conquer Kuruwa Plains III.",
        "achievementBadgeName": "501299"
      },
      {
        "gameId": 9611,
        "gameTitle": "The Abbey of Crime",
        "gameImageIcon": "/Images/054614.png",
        "gameImageTitle": "/Images/053184.png",
        "gameImageIngame": "/Images/053185.png",
        "gameImageBoxArt": "/Images/054983.png",
        "consoleID": 37,
        "consoleName": "Amstrad CPC",
        "achievementId": 203814,
        "achievementTitle": "Penitenziagite!",
        "achievementDescription": "[III] In which the papyrus is found and a mysterious monk is discovered.",
        "achievementBadgeName": "227274"
      },
      {
        "gameId": 1143,
        "gameTitle": "R-Type III: The Third Lightning",
        "gameImageIcon": "/Images/064800.png",
        "gameImageTitle": "/Images/035364.png",
        "gameImageIngame": "/Images/035365.png",
        "gameImageBoxArt": "/Images/064805.png",
        "consoleID": 3,
        "consoleName": "SNES/Super Famicom",
        "achievementId": 6204,
        "achievementTitle": "Stage 4 Cleared",
        "achievementDescription": "You've defeated Creature 666 [no level select]",
        "achievementBadgeName": "06639"
      },
      {
        "gameId": 784,
        "gameTitle": "Mega Man Zero 4",
        "gameImageIcon": "/Images/046277.png",
        "gameImageTitle": "/Images/033794.png",
        "gameImageIngame": "/Images/005210.png",
        "gameImageBoxArt": "/Images/005028.png",
        "consoleID": 5,
        "consoleName": "Game Boy Advance",
        "achievementId": 26466,
        "achievementTitle": "Global Warming",
        "achievementDescription": "Get through the Artifical Sun to halt the sun",
        "achievementBadgeName": "185266"
      }
    ]
  },
  {
    "gameId": 4618,
    "gameTitle": "The Flintstones: The Surprise at Dinosaur Peak!",
    "gameImageIcon": "/Images/012159.png",
    "gameImageTitle": "/Images/012157.png",
    "gameImageIngame": "/Images/012158.png",
    "gameImageBoxArt": "/Images/012156.png",
    "consoleID": 7,
    "consoleName": "NES/Famicom",
    "achievementId": 76423,
    "achievementTitle": "Witch's House",
    "achievementDescription": "Beat level 7 (Witch's House) (no debug mode)",
    "achievementBadgeName": "81514",
    "achievementDateStart": "2025-04-21T00:00:00.000000Z",
    "achievementDateEnd": "2025-04-28T00:00:00.000000Z",
    "swaps": [
      {
        "gameId": 273,
        "gameTitle": "Alien 3",
        "gameImageIcon": "/Images/049187.png",
        "gameImageTitle": "/Images/001236.png",
        "gameImageIngame": "/Images/001237.png",
        "gameImageBoxArt": "/Images/002034.png",
        "consoleID": 3,
        "consoleName": "SNES/Super Famicom",
        "achievementId": 451,
        "achievementTitle": "Stage 1 - The Corridor #12",
        "achievementDescription": "Complete the 1st stage",
        "achievementBadgeName": "18891"
      },
      {
        "gameId": 1858,
        "gameTitle": "Ninja Gaiden III: The Ancient Ship of Doom",
        "gameImageIcon": "/Images/033108.png",
        "gameImageTitle": "/Images/002632.png",
        "gameImageIngame": "/Images/002631.png",
        "gameImageBoxArt": "/Images/012661.png",
        "consoleID": 7,
        "consoleName": "NES/Famicom",
        "achievementId": 12177,
        "achievementTitle": "Fortress",
        "achievementDescription": "Defeat the BIO-NOID Doppelganger and clear Act 5",
        "achievementBadgeName": "451474"
      },
      {
        "gameId": 27859,
        "gameTitle": "Freestyle Metal X",
        "gameImageIcon": "/Images/098611.png",
        "gameImageTitle": "/Images/098612.png",
        "gameImageIngame": "/Images/098613.png",
        "gameImageBoxArt": "/Images/098616.png",
        "consoleID": 21,
        "consoleName": "PlayStation 2",
        "achievementId": 440541,
        "achievementTitle": "Rodeo Rise - Race",
        "achievementDescription": "Win the race in Rodeo Rise",
        "achievementBadgeName": "497216"
      },
      {
        "gameId": 989,
        "gameTitle": "Lamborghini American Challenge",
        "gameImageIcon": "/Images/046979.png",
        "gameImageTitle": "/Images/006022.png",
        "gameImageIngame": "/Images/006023.png",
        "gameImageBoxArt": "/Images/006024.png",
        "consoleID": 3,
        "consoleName": "SNES/Super Famicom",
        "achievementId": 46012,
        "achievementTitle": "Second Division",
        "achievementDescription": "Reach Division 2.",
        "achievementBadgeName": "60084"
      }
    ]
  },
  {
    "gameId": 11270,
    "gameTitle": "Final Fantasy VIII",
    "gameImageIcon": "/Images/070799.png",
    "gameImageTitle": "/Images/020141.png",
    "gameImageIngame": "/Images/020142.png",
    "gameImageBoxArt": "/Images/049133.png",
    "consoleID": 12,
    "consoleName": "PlayStation",
    "achievementId": 96418,
    "achievementTitle": "Dogs of War",
    "achievementDescription": "Complete your SeeD exam.",
    "achievementBadgeName": "105136",
    "achievementDateStart": "2025-04-28T00:00:00.000000Z",
    "achievementDateEnd": "2025-05-05T00:00:00.000000Z",
    "swaps": [
      {
        "gameId": 937,
        "gameTitle": "Home Alone 2: Lost in New York",
        "gameImageIcon": "/Images/009478.png",
        "gameImageTitle": "/Images/009474.png",
        "gameImageIngame": "/Images/009475.png",
        "gameImageBoxArt": "/Images/009473.png",
        "consoleID": 3,
        "consoleName": "SNES/Super Famicom",
        "achievementId": 43846,
        "achievementTitle": "It's the Best Place to Be (Super Edition)",
        "achievementDescription": "Finish the game",
        "achievementBadgeName": "44766"
      },
      {
        "gameId": 20377,
        "gameTitle": "Kaze no NOTAM",
        "gameImageIcon": "/Images/064028.png",
        "gameImageTitle": "/Images/063516.png",
        "gameImageIngame": "/Images/063517.png",
        "gameImageBoxArt": "/Images/063005.png",
        "consoleID": 12,
        "consoleName": "PlayStation",
        "achievementId": 266043,
        "achievementTitle": "Round 3 Expert",
        "achievementDescription": "Clear Round 3 - Pop a balloon under 1 minute",
        "achievementBadgeName": "294234"
      },
      {
        "gameId": 1020,
        "gameTitle": "MechWarrior",
        "gameImageIcon": "/Images/041875.png",
        "gameImageTitle": "/Images/041854.png",
        "gameImageIngame": "/Images/041855.png",
        "gameImageBoxArt": "/Images/041856.png",
        "consoleID": 3,
        "consoleName": "SNES/Super Famicom",
        "achievementId": 141263,
        "achievementTitle": "Alpha",
        "achievementDescription": "Defeat Wolf Glupper",
        "achievementBadgeName": "157368"
      },
      {
        "gameId": 23989,
        "gameTitle": "Gothik",
        "gameImageIcon": "/Images/072059.png",
        "gameImageTitle": "/Images/072060.png",
        "gameImageIngame": "/Images/072057.png",
        "gameImageBoxArt": "/Images/072058.png",
        "consoleID": 37,
        "consoleName": "Amstrad CPC",
        "achievementId": 313201,
        "achievementTitle": "Lone Wolf",
        "achievementDescription": "Complete level 4.",
        "achievementBadgeName": "346415"
      }
    ]
  },
  {
    "gameId": 2588,
    "gameTitle": "Summon Night: Swordcraft Story",
    "gameImageIcon": "/Images/036473.png",
    "gameImageTitle": "/Images/010288.png",
    "gameImageIngame": "/Images/010289.png",
    "gameImageBoxArt": "/Images/007653.png",
    "consoleID": 5,
    "consoleName": "Game Boy Advance",
    "achievementId": 49123,
    "achievementTitle": "A Sword is Not Strength",
    "achievementDescription": "Complete the 2nd day.",
    "achievementBadgeName": "49740",
    "achievementDateStart": "2025-05-05T00:00:00.000000Z",
    "achievementDateEnd": "2025-05-12T00:00:00.000000Z",
    "swaps": [
      {
        "gameId": 913,
        "gameTitle": "First Samurai",
        "gameImageIcon": "/Images/077040.png",
        "gameImageTitle": "/Images/074421.png",
        "gameImageIngame": "/Images/074422.png",
        "gameImageBoxArt": "/Images/074423.png",
        "consoleID": 3,
        "consoleName": "SNES/Super Famicom",
        "achievementId": 372409,
        "achievementTitle": "Suisei",
        "achievementDescription": "Slay Suisei.",
        "achievementBadgeName": "419509"
      },
      {
        "gameId": 6710,
        "gameTitle": "Yu-Gi-Oh! 5D's Tag Force 5",
        "gameImageIcon": "/Images/048258.png",
        "gameImageTitle": "/Images/053433.png",
        "gameImageIngame": "/Images/053432.png",
        "gameImageBoxArt": "/Images/047860.png",
        "consoleID": 41,
        "consoleName": "PlayStation Portable",
        "achievementId": 198258,
        "achievementTitle": "Slugger",
        "achievementDescription": "[Story Mode] Caused 10,000 or more points of battle damage during a duel",
        "achievementBadgeName": "220283"
      },
      {
        "gameId": 12652,
        "gameTitle": "Sonic the Hedgehog 2",
        "gameImageIcon": "/Images/107953.png",
        "gameImageTitle": "/Images/016961.png",
        "gameImageIngame": "/Images/016963.png",
        "gameImageBoxArt": "/Images/016964.png",
        "consoleID": 15,
        "consoleName": "Game Gear",
        "achievementId": 71106,
        "achievementTitle": "Factory Shutdown",
        "achievementDescription": "Clear Gimmick Mountain Zone.",
        "achievementBadgeName": "67296"
      },
      {
        "gameId": 11395,
        "gameTitle": "Dead or Alive",
        "gameImageIcon": "/Images/027261.png",
        "gameImageTitle": "/Images/046127.png",
        "gameImageIngame": "/Images/046126.png",
        "gameImageBoxArt": "/Images/046125.png",
        "consoleID": 12,
        "consoleName": "PlayStation",
        "achievementId": 160920,
        "achievementTitle": "Hayabusa",
        "achievementDescription": "Beat every fighter in Tournament mode with Hayabusa (Default Game Options).",
        "achievementBadgeName": "180887"
      }
    ]
  },
  {
    "gameId": 2663,
    "gameTitle": "Disaster Report | SOS: The Final Escape | Zettai Zetsumei Toshi",
    "gameImageIcon": "/Images/052679.png",
    "gameImageTitle": "/Images/091858.png",
    "gameImageIngame": "/Images/091863.png",
    "gameImageBoxArt": "/Images/052786.png",
    "consoleID": 21,
    "consoleName": "PlayStation 2",
    "achievementId": 460887,
    "achievementTitle": "Aspiring Journalist",
    "achievementDescription": "Meet a freelance photographer.",
    "achievementBadgeName": "521967",
    "achievementDateStart": "2025-05-12T00:00:00.000000Z",
    "achievementDateEnd": "2025-05-19T00:00:00.000000Z",
    "swaps": [
      {
        "gameId": 12611,
        "gameTitle": "Ninja Gaiden | Shadow Warriors | Ninja Ryukenden",
        "gameImageIcon": "/Images/095082.png",
        "gameImageTitle": "/Images/029171.png",
        "gameImageIngame": "/Images/029172.png",
        "gameImageBoxArt": "/Images/095081.png",
        "consoleID": 27,
        "consoleName": "Arcade",
        "achievementId": 459261,
        "achievementTitle": "Canyon Crosser",
        "achievementDescription": "Clear Round 4 on standard settings or harder.",
        "achievementBadgeName": "519952"
      },
      {
        "gameId": 12864,
        "gameTitle": "Detective Conan: Legend of the Treasure of Strange Rock Island",
        "gameImageIcon": "/Images/073581.png",
        "gameImageTitle": "/Images/017554.png",
        "gameImageIngame": "/Images/019720.png",
        "gameImageBoxArt": "/Images/017553.png",
        "consoleID": 6,
        "consoleName": "Game Boy Color",
        "achievementId": 67189,
        "achievementTitle": "The important evidence",
        "achievementDescription": "Get the important evidence in this case.",
        "achievementBadgeName": "71023"
      },
      {
        "gameId": 1223,
        "gameTitle": "Super Nova | Darius Force",
        "gameImageIcon": "/Images/047440.png",
        "gameImageTitle": "/Images/047441.png",
        "gameImageIngame": "/Images/047442.png",
        "gameImageBoxArt": "/Images/023028.png",
        "consoleID": 3,
        "consoleName": "SNES/Super Famicom",
        "achievementId": 170163,
        "achievementTitle": "Metal Spiral Snail",
        "achievementDescription": "Clear Zone F.",
        "achievementBadgeName": "191159"
      },
      {
        "gameId": 6427,
        "gameTitle": "Yu-Gi-Oh! ARC-V Tag Force Special",
        "gameImageIcon": "/Images/048259.png",
        "gameImageTitle": "/Images/075585.png",
        "gameImageIngame": "/Images/075586.png",
        "gameImageBoxArt": "/Images/047864.png",
        "consoleID": 41,
        "consoleName": "PlayStation Portable",
        "achievementId": 330066,
        "achievementTitle": "Dark Duelist's Debut",
        "achievementDescription": "Complete the 1st heart event of Yami Yugi",
        "achievementBadgeName": "372352"
      }
    ]
  }
]
